xkid/__init__.py
xkid/attest.py
xkid/canon.py
xkid/canonjson.py
xkid/cert.py
xkid/claim.py
xkid/device.py
xkid/device_id.py
xkid/hashing.py
xkid/hashutil.py
xkid/ial_legacy.py
xkid/insance.py
xkid/instance.py
xkid/keys.py
xkid/promotion.py
xkid/revocation.py
xkid/sysop.py
xkid/trust.py
xkid/verify.py
xkid/world_ledger.py
xkid/cli/__init__.py
xkid/cli/app.py
xkid/cli/contract.py
xkid/cli/emit.py
xkid/cli/thermalpaste.py
xkid/core/__init__.py
xkid/core/canonical.py
xkid/core/result.py
xkid/device/__init__.py
xkid/device/policy.py
xkid/device/provider_api.py
xkid/device/registry.py
xkid/device/providers/default.py
xkid/device/providers/soft.py
xkid/ial/__init__.py
xkid/id/__init__.py
xkid/id/digest.py
xkid/id/entrogravity.py
xkid/id/v1.py
xkid/lenses/__init__.py
xkid/lenses/plugin_api.py
xkid/lenses/registry.py
xkid/lenses/builtin/__init__.py
xkid/lenses/builtin/digest.py
xkid/lenses/builtin/oscillation.py
xkid/packet/__init__.py
xkid/packet/bind.py
xkid/thermalpaste/__init__.py
xkid/thermalpaste/provider_api.py
xkid/thermalpaste/types.py
xkid/thermalpaste/providers/null_provider.py
xkid/world/__init__.py
xkid-0.0.1.dist-info/METADATA
xkid-0.0.1.dist-info/WHEEL
xkid-0.0.1.dist-info/entry_points.txt
xkid-0.0.1.dist-info/top_level.txt
xkid-0.0.1.dist-info/RECORD
