Metadata-Version: 2.4
Name: xkid
Version: 0.0.1
Requires-Dist: b32k>=0.0.2
Requires-Dist: xkernel>=0.0.1
Requires-Dist: cryptography>=42.0.0
